OneNeuron/__init__.py
OneNeuron/perceptron.py
oneneuron_pypi_keithferns98-0.0.2.dist-info/LICENSE
oneneuron_pypi_keithferns98-0.0.2.dist-info/METADATA
oneneuron_pypi_keithferns98-0.0.2.dist-info/WHEEL
oneneuron_pypi_keithferns98-0.0.2.dist-info/top_level.txt
oneneuron_pypi_keithferns98-0.0.2.dist-info/RECORD
