Metadata-Version: 2.1
Name: oneneuron-pypi-keithferns98
Version: 0.0.2
Summary: Perceptron package
Home-page: https://github.com/keithferns98/oneneuron_pypi
Author: keithferns98
Author-email: keithfernandes311@gmail.com
License: UNKNOWN
Project-URL: Bug Tracker, https://github.com/keithferns98/oneneuron_pypi/issues
Platform: UNKNOWN
Classifier: Programming Language :: Python :: 3
Classifier: License :: OSI Approved :: MIT License
Classifier: Operating System :: OS Independent
Requires-Python: >=3.7
License-File: LICENSE
Requires-Dist: numpy
Requires-Dist: tqdm
